{
  "id": "districts_streamers",
  "class_id": "class_streamers",
  "districts": [
    {
      "id": "district_neon_drift",
      "name": "ネオン・ドリフト",
      "avg_land_price": 5000,
      "population": 2250000,
      "description": "配信スタジオとライブバーが密集する通り。"
    },
    {
      "id": "district_hype_square",
      "name": "ハイプ・スクエア",
      "avg_land_price": 5200,
      "population": 2250000,
      "description": "イベント広場。毎夜フェスと宣伝ホロで騒がしい。"
    },
    {
      "id": "district_virtual_arena",
      "name": "バーチャル・アリーナ",
      "avg_land_price": 4800,
      "population": 2250000,
      "description": "VR競技場とスポンサーラウンジが併設。"
    },
    {
      "id": "district_echo_mall",
      "name": "エコー・モール",
      "avg_land_price": 4500,
      "population": 2250000,
      "description": "ショッピングと体験型広告の混合施設。"
    },
    {
      "id": "district_chroma_tower",
      "name": "クロマ・タワー",
      "avg_land_price": 4700,
      "population": 2250000,
      "description": "クリエイター向けサブス住宅兼オフィス。"
    },
    {
      "id": "district_liveline_avenue",
      "name": "ライブライン・アベニュー",
      "avg_land_price": 4300,
      "population": 2250000,
      "description": "路上配信が許可された特区。トラブルも多い。"
    },
    {
      "id": "district_spectrum_park",
      "name": "スペクトラム・パーク",
      "avg_land_price": 4100,
      "population": 2250000,
      "description": "野外ステージと屋台群。深夜も人が絶えない。"
    },
    {
      "id": "district_stage_zero",
      "name": "ステージ・ゼロ",
      "avg_land_price": 4000,
      "population": 2250000,
      "description": "新人発掘の登竜門。安価なスタジオが並ぶ。"
    }
  ]
}
